{"openapi":"3.1.0","info":{"title":"EcomHub API","version":"v1"},"servers":[{"url":"http://localhost:8081","description":"Development"}],"security":[{"bearerAuth":[]}],"tags":[{"name":"Permission API","description":"Operations related to permission management"},{"name":"Account API","description":"Endpoints related to account management"},{"name":"Role API","description":"Operations related to role management"}],"paths":{"/api/v1/auth/role/{roleId}/grant/permission":{"put":{"tags":["Role API"],"summary":"Grant permission to role","description":"Grant a specific permission to a role","operationId":"grantPermission","parameters":[{"name":"roleId","in":"path","required":true,"schema":{"type":"string","format":"uuid"}}],"requestBody":{"content":{"application/json":{"schema":{"$ref":"#/components/schemas/GrantPermissionRequest"}}},"required":true},"responses":{"200":{"description":"Successful","content":{"application/json":{"schema":{"properties":{"statusCode":{"type":"integer","format":"int32"},"errorCode":{"type":"string"},"message":{"type":"string"},"data":{}}}}}},"400":{"description":"Permission information is required","content":{"application/json":{"schema":{"properties":{"statusCode":{"type":"integer","format":"int32"},"errorCode":{"type":"string"},"message":{"type":"string"},"data":{"type":"object"}}},"example":"{\n  \"statusCode\": 400,\n  \"errorCode\": \"REQUIRED_FIELD_MISSING\",\n  \"message\": \"Permission information is required\",\n  \"data\": null\n}\n"}}},"404":{"description":"Sorry, we couldn't find the role or permission you are looking for","content":{"application/json":{"schema":{"properties":{"statusCode":{"type":"integer","format":"int32"},"errorCode":{"type":"string"},"message":{"type":"string"},"data":{"type":"object"}}},"example":"{\n  \"statusCode\": 404,\n  \"errorCode\": \"RESOURCE_NOT_FOUND\",\n  \"message\": \"Sorry, we couldn't find the role or permission you are looking for\",\n  \"data\": null\n}\n"}}},"403":{"description":"You do not have sufficient permissions to grant permissions to roles","content":{"application/json":{"schema":{"properties":{"statusCode":{"type":"integer","format":"int32"},"errorCode":{"type":"string"},"message":{"type":"string"},"data":{"type":"object"}}},"example":"{\n  \"statusCode\": 403,\n  \"errorCode\": \"FORBIDDEN\",\n  \"message\": \"You do not have sufficient permissions to grant permissions to roles\",\n  \"data\": null\n}\n"}}},"409":{"description":"Permission is already assigned to this role","content":{"application/json":{"schema":{"properties":{"statusCode":{"type":"integer","format":"int32"},"errorCode":{"type":"string"},"message":{"type":"string"},"data":{"type":"object"}}},"example":"{\n  \"statusCode\": 409,\n  \"errorCode\": \"DUPLICATE_ENTRY\",\n  \"message\": \"Permission is already assigned to this role\",\n  \"data\": null\n}\n"}}}}}},"/api/v1/auth/account/{accountId}/role/assign":{"put":{"tags":["Account API"],"summary":"Assign role to account","description":"Assign role to account","operationId":"grantRole","parameters":[{"name":"accountId","in":"path","required":true,"schema":{"type":"string","format":"uuid"}}],"requestBody":{"content":{"application/json":{"schema":{"type":"string","format":"uuid"}}},"required":true},"responses":{"200":{"description":"Successful","content":{"application/json":{"schema":{"properties":{"statusCode":{"type":"integer","format":"int32"},"errorCode":{"type":"string"},"message":{"type":"string"},"data":{}}}}}},"400":{"description":"Please select a role to assign to the account","content":{"application/json":{"schema":{"properties":{"statusCode":{"type":"integer","format":"int32"},"errorCode":{"type":"string"},"message":{"type":"string"},"data":{"type":"object"}}},"example":"{\n  \"statusCode\": 400,\n  \"errorCode\": \"REQUIRED_FIELD_MISSING\",\n  \"message\": \"Please select a role to assign to the account\",\n  \"data\": null\n}\n"}}},"404":{"description":"Sorry, we couldn't find the role you are looking for","content":{"application/json":{"schema":{"properties":{"statusCode":{"type":"integer","format":"int32"},"errorCode":{"type":"string"},"message":{"type":"string"},"data":{"type":"object"}}},"example":"{\n  \"statusCode\": 404,\n  \"errorCode\": \"RESOURCE_NOT_FOUND\",\n  \"message\": \"Sorry, we couldn't find the role you are looking for\",\n  \"data\": null\n}\n"}}},"403":{"description":"You do not have sufficient permissions to assign a role to the account.","content":{"application/json":{"schema":{"properties":{"statusCode":{"type":"integer","format":"int32"},"errorCode":{"type":"string"},"message":{"type":"string"},"data":{"type":"object"}}},"example":"{\n  \"statusCode\": 403,\n  \"errorCode\": \"FORBIDDEN\",\n  \"message\": \"You do not have sufficient permissions to assign a role to the account.\",\n  \"data\": null\n}\n"}}},"409":{"description":"The role 'admin' already exists.","content":{"application/json":{"schema":{"properties":{"statusCode":{"type":"integer","format":"int32"},"errorCode":{"type":"string"},"message":{"type":"string"},"data":{"type":"object"}}},"example":"{\n  \"statusCode\": 409,\n  \"errorCode\": \"DUPLICATE_ENTRY\",\n  \"message\": \"The role 'admin' already exists.\",\n  \"data\": null\n}\n"}}}}}},"/api/v1/auth/role":{"get":{"tags":["Role API"],"summary":"Get all roles","description":"Retrieve all available roles in the system","operationId":"getAll","responses":{"200":{"description":"Successful","content":{"application/json":{"schema":{"properties":{"statusCode":{"type":"integer","format":"int32"},"errorCode":{"type":"string"},"message":{"type":"string"},"data":{"type":"array","items":{"properties":{"id":{"type":"string","format":"uuid"},"name":{"type":"string"},"key":{"type":"string"},"type":{"type":"string"},"status":{"type":"string"},"description":{"type":"string"},"level":{"type":"integer","format":"int32"},"permissions":{"type":"array","items":{"$ref":"#/components/schemas/PermissionResponse"}}}}}}}}}},"403":{"description":"You do not have sufficient permissions to view roles","content":{"application/json":{"schema":{"properties":{"statusCode":{"type":"integer","format":"int32"},"errorCode":{"type":"string"},"message":{"type":"string"},"data":{"type":"object"}}},"example":"{\n  \"statusCode\": 403,\n  \"errorCode\": \"FORBIDDEN\",\n  \"message\": \"You do not have sufficient permissions to view roles\",\n  \"data\": null\n}\n"}}}}},"post":{"tags":["Role API"],"summary":"Add new role","description":"Create a new role in the system","operationId":"add","requestBody":{"content":{"application/json":{"schema":{"$ref":"#/components/schemas/AddRoleRequest"}}},"required":true},"responses":{"200":{"description":"Successful","content":{"application/json":{"schema":{"properties":{"statusCode":{"type":"integer","format":"int32"},"errorCode":{"type":"string"},"message":{"type":"string"},"data":{}}}}}},"400":{"description":"Role information is required","content":{"application/json":{"schema":{"properties":{"statusCode":{"type":"integer","format":"int32"},"errorCode":{"type":"string"},"message":{"type":"string"},"data":{"type":"object"}}},"example":"{\n  \"statusCode\": 400,\n  \"errorCode\": \"REQUIRED_FIELD_MISSING\",\n  \"message\": \"Role information is required\",\n  \"data\": null\n}\n"}}},"409":{"description":"Role with this name already exists","content":{"application/json":{"schema":{"properties":{"statusCode":{"type":"integer","format":"int32"},"errorCode":{"type":"string"},"message":{"type":"string"},"data":{"type":"object"}}},"example":"{\n  \"statusCode\": 409,\n  \"errorCode\": \"RESOURCE_ALREADY_EXISTS\",\n  \"message\": \"Role with this name already exists\",\n  \"data\": null\n}\n"}}},"403":{"description":"You do not have sufficient permissions to create roles","content":{"application/json":{"schema":{"properties":{"statusCode":{"type":"integer","format":"int32"},"errorCode":{"type":"string"},"message":{"type":"string"},"data":{"type":"object"}}},"example":"{\n  \"statusCode\": 403,\n  \"errorCode\": \"FORBIDDEN\",\n  \"message\": \"You do not have sufficient permissions to create roles\",\n  \"data\": null\n}\n"}}}}}},"/api/v1/auth/account/register":{"post":{"tags":["Account API"],"summary":"Register account","description":"Register account with basic information","operationId":"registerAccount","requestBody":{"content":{"application/json":{"schema":{"$ref":"#/components/schemas/RegisterBasicRequest"}}},"required":true},"responses":{"200":{"description":"Successful","content":{"application/json":{"schema":{"properties":{"statusCode":{"type":"integer","format":"int32"},"errorCode":{"type":"string"},"message":{"type":"string"},"data":{}}}}}},"400":{"description":"Please enter your email","content":{"application/json":{"schema":{"properties":{"statusCode":{"type":"integer","format":"int32"},"errorCode":{"type":"string"},"message":{"type":"string"},"data":{"type":"object"}}},"example":"{\n  \"statusCode\": 400,\n  \"errorCode\": \"REQUIRED_FIELD_MISSING\",\n  \"message\": \"Please enter your email\",\n  \"data\": null\n}\n"}}},"404":{"description":"Sorry, we couldn't find the role you are looking for","content":{"application/json":{"schema":{"properties":{"statusCode":{"type":"integer","format":"int32"},"errorCode":{"type":"string"},"message":{"type":"string"},"data":{"type":"object"}}},"example":"{\n  \"statusCode\": 404,\n  \"errorCode\": \"RESOURCE_NOT_FOUND\",\n  \"message\": \"Sorry, we couldn't find the role you are looking for\",\n  \"data\": null\n}\n"}}},"409":{"description":"User with email 'abc@gmail.com' already exists","content":{"application/json":{"schema":{"properties":{"statusCode":{"type":"integer","format":"int32"},"errorCode":{"type":"string"},"message":{"type":"string"},"data":{"type":"object"}}},"example":"{\n  \"statusCode\": 409,\n  \"errorCode\": \"RESOURCE_ALREADY_EXISTS\",\n  \"message\": \"User with email 'abc@gmail.com' already exists\",\n  \"data\": null\n}\n"}}}}}},"/api/v1/auth/role/{roleId}/name":{"patch":{"tags":["Role API"],"summary":"Update role name","description":"Update the name of a specific role","operationId":"updateName","parameters":[{"name":"roleId","in":"path","required":true,"schema":{"type":"string","format":"uuid"}}],"requestBody":{"description":"The new name of the role","content":{"application/json":{"schema":{"type":"string"}}},"required":true},"responses":{"200":{"description":"Successful","content":{"application/json":{"schema":{"properties":{"statusCode":{"type":"integer","format":"int32"},"errorCode":{"type":"string"},"message":{"type":"string"},"data":{}}}}}},"400":{"description":"Role name is required","content":{"application/json":{"schema":{"properties":{"statusCode":{"type":"integer","format":"int32"},"errorCode":{"type":"string"},"message":{"type":"string"},"data":{"type":"object"}}},"example":"{\n  \"statusCode\": 400,\n  \"errorCode\": \"REQUIRED_FIELD_MISSING\",\n  \"message\": \"Role name is required\",\n  \"data\": null\n}\n"}}},"404":{"description":"Sorry, we couldn't find the role you are looking for","content":{"application/json":{"schema":{"properties":{"statusCode":{"type":"integer","format":"int32"},"errorCode":{"type":"string"},"message":{"type":"string"},"data":{"type":"object"}}},"example":"{\n  \"statusCode\": 404,\n  \"errorCode\": \"RESOURCE_NOT_FOUND\",\n  \"message\": \"Sorry, we couldn't find the role you are looking for\",\n  \"data\": null\n}\n"}}},"403":{"description":"You do not have sufficient permissions to update role names","content":{"application/json":{"schema":{"properties":{"statusCode":{"type":"integer","format":"int32"},"errorCode":{"type":"string"},"message":{"type":"string"},"data":{"type":"object"}}},"example":"{\n  \"statusCode\": 403,\n  \"errorCode\": \"FORBIDDEN\",\n  \"message\": \"You do not have sufficient permissions to update role names\",\n  \"data\": null\n}\n"}}},"409":{"description":"Role with this name already exists","content":{"application/json":{"schema":{"properties":{"statusCode":{"type":"integer","format":"int32"},"errorCode":{"type":"string"},"message":{"type":"string"},"data":{"type":"object"}}},"example":"{\n  \"statusCode\": 409,\n  \"errorCode\": \"DUPLICATE_ENTRY\",\n  \"message\": \"Role with this name already exists\",\n  \"data\": null\n}\n"}}}}}},"/api/v1/auth/role/{roleId}/level":{"patch":{"tags":["Role API"],"summary":"Update role level","description":"Update the level of a specific role","operationId":"updateLevel","parameters":[{"name":"roleId","in":"path","required":true,"schema":{"type":"string","format":"uuid"}}],"requestBody":{"description":"The new level of the role","content":{"application/json":{"schema":{"type":"integer","format":"int32"}}},"required":true},"responses":{"200":{"description":"Successful","content":{"application/json":{"schema":{"properties":{"statusCode":{"type":"integer","format":"int32"},"errorCode":{"type":"string"},"message":{"type":"string"},"data":{}}}}}},"400":{"description":"Role level must be a valid integer","content":{"application/json":{"schema":{"properties":{"statusCode":{"type":"integer","format":"int32"},"errorCode":{"type":"string"},"message":{"type":"string"},"data":{"type":"object"}}},"example":"{\n  \"statusCode\": 400,\n  \"errorCode\": \"INVALID_VALUE\",\n  \"message\": \"Role level must be a valid integer\",\n  \"data\": null\n}\n"}}},"404":{"description":"Sorry, we couldn't find the role you are looking for","content":{"application/json":{"schema":{"properties":{"statusCode":{"type":"integer","format":"int32"},"errorCode":{"type":"string"},"message":{"type":"string"},"data":{"type":"object"}}},"example":"{\n  \"statusCode\": 404,\n  \"errorCode\": \"RESOURCE_NOT_FOUND\",\n  \"message\": \"Sorry, we couldn't find the role you are looking for\",\n  \"data\": null\n}\n"}}},"403":{"description":"You do not have sufficient permissions to update role levels","content":{"application/json":{"schema":{"properties":{"statusCode":{"type":"integer","format":"int32"},"errorCode":{"type":"string"},"message":{"type":"string"},"data":{"type":"object"}}},"example":"{\n  \"statusCode\": 403,\n  \"errorCode\": \"FORBIDDEN\",\n  \"message\": \"You do not have sufficient permissions to update role levels\",\n  \"data\": null\n}\n"}}}}}},"/api/v1/auth/role/{roleId}/description":{"patch":{"tags":["Role API"],"summary":"Update role description","description":"Update the description of a specific role","operationId":"updateDescription","parameters":[{"name":"roleId","in":"path","required":true,"schema":{"type":"string","format":"uuid"}}],"requestBody":{"description":"The new description of the role","content":{"application/json":{"schema":{"type":"string"}}},"required":true},"responses":{"200":{"description":"Successful","content":{"application/json":{"schema":{"properties":{"statusCode":{"type":"integer","format":"int32"},"errorCode":{"type":"string"},"message":{"type":"string"},"data":{}}}}}},"400":{"description":"Role description is required","content":{"application/json":{"schema":{"properties":{"statusCode":{"type":"integer","format":"int32"},"errorCode":{"type":"string"},"message":{"type":"string"},"data":{"type":"object"}}},"example":"{\n  \"statusCode\": 400,\n  \"errorCode\": \"REQUIRED_FIELD_MISSING\",\n  \"message\": \"Role description is required\",\n  \"data\": null\n}\n"}}},"404":{"description":"Sorry, we couldn't find the role you are looking for","content":{"application/json":{"schema":{"properties":{"statusCode":{"type":"integer","format":"int32"},"errorCode":{"type":"string"},"message":{"type":"string"},"data":{"type":"object"}}},"example":"{\n  \"statusCode\": 404,\n  \"errorCode\": \"RESOURCE_NOT_FOUND\",\n  \"message\": \"Sorry, we couldn't find the role you are looking for\",\n  \"data\": null\n}\n"}}},"403":{"description":"You do not have sufficient permissions to update role descriptions","content":{"application/json":{"schema":{"properties":{"statusCode":{"type":"integer","format":"int32"},"errorCode":{"type":"string"},"message":{"type":"string"},"data":{"type":"object"}}},"example":"{\n  \"statusCode\": 403,\n  \"errorCode\": \"FORBIDDEN\",\n  \"message\": \"You do not have sufficient permissions to update role descriptions\",\n  \"data\": null\n}\n"}}}}}},"/api/v1/auth/permission/{permissionId}/name":{"patch":{"tags":["Permission API"],"summary":"Update permission name","description":"Update the name of a specific permission","operationId":"updateName_1","parameters":[{"name":"permissionId","in":"path","required":true,"schema":{"type":"string","format":"uuid"}}],"requestBody":{"description":"The new name of the permission","content":{"application/json":{"schema":{"type":"string"}}},"required":true},"responses":{"200":{"description":"Successful","content":{"application/json":{"schema":{"properties":{"statusCode":{"type":"integer","format":"int32"},"errorCode":{"type":"string"},"message":{"type":"string"},"data":{}}}}}},"400":{"description":"Permission name is required","content":{"application/json":{"schema":{"properties":{"statusCode":{"type":"integer","format":"int32"},"errorCode":{"type":"string"},"message":{"type":"string"},"data":{"type":"object"}}},"example":"{\n  \"statusCode\": 400,\n  \"errorCode\": \"REQUIRED_FIELD_MISSING\",\n  \"message\": \"Permission name is required\",\n  \"data\": null\n}\n"}}},"404":{"description":"Sorry, we couldn't find the permission you are looking for","content":{"application/json":{"schema":{"properties":{"statusCode":{"type":"integer","format":"int32"},"errorCode":{"type":"string"},"message":{"type":"string"},"data":{"type":"object"}}},"example":"{\n  \"statusCode\": 404,\n  \"errorCode\": \"RESOURCE_NOT_FOUND\",\n  \"message\": \"Sorry, we couldn't find the permission you are looking for\",\n  \"data\": null\n}\n"}}},"403":{"description":"You do not have sufficient permissions to update permission names","content":{"application/json":{"schema":{"properties":{"statusCode":{"type":"integer","format":"int32"},"errorCode":{"type":"string"},"message":{"type":"string"},"data":{"type":"object"}}},"example":"{\n  \"statusCode\": 403,\n  \"errorCode\": \"FORBIDDEN\",\n  \"message\": \"You do not have sufficient permissions to update permission names\",\n  \"data\": null\n}\n"}}}}}},"/api/v1/auth/permission/{permissionId}/description":{"patch":{"tags":["Permission API"],"summary":"Update permission description","description":"Update the description of a specific permission","operationId":"updateDescription_1","parameters":[{"name":"permissionId","in":"path","required":true,"schema":{"type":"string","format":"uuid"}}],"requestBody":{"description":"The new description of the permission","content":{"application/json":{"schema":{"type":"string"}}},"required":true},"responses":{"200":{"description":"Successful","content":{"application/json":{"schema":{"properties":{"statusCode":{"type":"integer","format":"int32"},"errorCode":{"type":"string"},"message":{"type":"string"},"data":{}}}}}},"400":{"description":"Permission description is required","content":{"application/json":{"schema":{"properties":{"statusCode":{"type":"integer","format":"int32"},"errorCode":{"type":"string"},"message":{"type":"string"},"data":{"type":"object"}}},"example":"{\n  \"statusCode\": 400,\n  \"errorCode\": \"REQUIRED_FIELD_MISSING\",\n  \"message\": \"Permission description is required\",\n  \"data\": null\n}\n"}}},"404":{"description":"Sorry, we couldn't find the permission you are looking for","content":{"application/json":{"schema":{"properties":{"statusCode":{"type":"integer","format":"int32"},"errorCode":{"type":"string"},"message":{"type":"string"},"data":{"type":"object"}}},"example":"{\n  \"statusCode\": 404,\n  \"errorCode\": \"RESOURCE_NOT_FOUND\",\n  \"message\": \"Sorry, we couldn't find the permission you are looking for\",\n  \"data\": null\n}\n"}}},"403":{"description":"You do not have sufficient permissions to update permission descriptions","content":{"application/json":{"schema":{"properties":{"statusCode":{"type":"integer","format":"int32"},"errorCode":{"type":"string"},"message":{"type":"string"},"data":{"type":"object"}}},"example":"{\n  \"statusCode\": 403,\n  \"errorCode\": \"FORBIDDEN\",\n  \"message\": \"You do not have sufficient permissions to update permission descriptions\",\n  \"data\": null\n}\n"}}}}}},"/api/v1/auth/permission":{"get":{"tags":["Permission API"],"summary":"Get all permissions","description":"Retrieve all available permissions in the system","operationId":"getAllPermission","responses":{"200":{"description":"Successful","content":{"application/json":{"schema":{"properties":{"statusCode":{"type":"integer","format":"int32"},"errorCode":{"type":"string"},"message":{"type":"string"},"data":{"type":"array","items":{"properties":{"id":{"type":"string","format":"uuid"},"name":{"type":"string"},"key":{"type":"string"},"description":{"type":"string"}}}}}}}}},"403":{"description":"You do not have sufficient permissions to view permissions","content":{"application/json":{"schema":{"properties":{"statusCode":{"type":"integer","format":"int32"},"errorCode":{"type":"string"},"message":{"type":"string"},"data":{"type":"object"}}},"example":"{\n  \"statusCode\": 403,\n  \"errorCode\": \"FORBIDDEN\",\n  \"message\": \"You do not have sufficient permissions to view permissions\",\n  \"data\": null\n}\n"}}}}}},"/api/v1/auth/role/{roleId}":{"delete":{"tags":["Role API"],"summary":"Delete role","description":"Delete a specific role from the system","operationId":"delete","parameters":[{"name":"roleId","in":"path","required":true,"schema":{"type":"string","format":"uuid"}}],"responses":{"200":{"description":"Successful","content":{"application/json":{"schema":{"properties":{"statusCode":{"type":"integer","format":"int32"},"errorCode":{"type":"string"},"message":{"type":"string"},"data":{}}}}}},"400":{"description":"Role ID is required","content":{"application/json":{"schema":{"properties":{"statusCode":{"type":"integer","format":"int32"},"errorCode":{"type":"string"},"message":{"type":"string"},"data":{"type":"object"}}},"example":"{\n  \"statusCode\": 400,\n  \"errorCode\": \"REQUIRED_FIELD_MISSING\",\n  \"message\": \"Role ID is required\",\n  \"data\": null\n}\n"}}},"404":{"description":"Sorry, we couldn't find the role you are looking for","content":{"application/json":{"schema":{"properties":{"statusCode":{"type":"integer","format":"int32"},"errorCode":{"type":"string"},"message":{"type":"string"},"data":{"type":"object"}}},"example":"{\n  \"statusCode\": 404,\n  \"errorCode\": \"RESOURCE_NOT_FOUND\",\n  \"message\": \"Sorry, we couldn't find the role you are looking for\",\n  \"data\": null\n}\n"}}},"403":{"description":"You do not have sufficient permissions to delete roles","content":{"application/json":{"schema":{"properties":{"statusCode":{"type":"integer","format":"int32"},"errorCode":{"type":"string"},"message":{"type":"string"},"data":{"type":"object"}}},"example":"{\n  \"statusCode\": 403,\n  \"errorCode\": \"FORBIDDEN\",\n  \"message\": \"You do not have sufficient permissions to delete roles\",\n  \"data\": null\n}\n"}}}}}},"/api/v1/auth/role/{roleId}/revoke/permission/{permissionId}":{"delete":{"tags":["Role API"],"summary":"Revoke permission from role","description":"Revoke a specific permission from a role","operationId":"revokePermission","parameters":[{"name":"roleId","in":"path","required":true,"schema":{"type":"string","format":"uuid"}},{"name":"permissionId","in":"path","required":true,"schema":{"type":"string","format":"uuid"}}],"responses":{"200":{"description":"Successful","content":{"application/json":{"schema":{"properties":{"statusCode":{"type":"integer","format":"int32"},"errorCode":{"type":"string"},"message":{"type":"string"},"data":{}}}}}},"400":{"description":"Permission ID is required","content":{"application/json":{"schema":{"properties":{"statusCode":{"type":"integer","format":"int32"},"errorCode":{"type":"string"},"message":{"type":"string"},"data":{"type":"object"}}},"example":"{\n  \"statusCode\": 400,\n  \"errorCode\": \"REQUIRED_FIELD_MISSING\",\n  \"message\": \"Permission ID is required\",\n  \"data\": null\n}\n"}}},"404":{"description":"Sorry, we couldn't find the role or permission you are looking for","content":{"application/json":{"schema":{"properties":{"statusCode":{"type":"integer","format":"int32"},"errorCode":{"type":"string"},"message":{"type":"string"},"data":{"type":"object"}}},"example":"{\n  \"statusCode\": 404,\n  \"errorCode\": \"RESOURCE_NOT_FOUND\",\n  \"message\": \"Sorry, we couldn't find the role or permission you are looking for\",\n  \"data\": null\n}\n"}}},"403":{"description":"You do not have sufficient permissions to revoke permissions from roles","content":{"application/json":{"schema":{"properties":{"statusCode":{"type":"integer","format":"int32"},"errorCode":{"type":"string"},"message":{"type":"string"},"data":{"type":"object"}}},"example":"{\n  \"statusCode\": 403,\n  \"errorCode\": \"FORBIDDEN\",\n  \"message\": \"You do not have sufficient permissions to revoke permissions from roles\",\n  \"data\": null\n}\n"}}}}}},"/api/v1/auth/account/{accountId}/role/{roleId}/revoke":{"delete":{"tags":["Account API"],"summary":"Revoke role from account","description":"Revoke role from account","operationId":"revokeRole","parameters":[{"name":"roleId","in":"path","required":true,"schema":{"type":"string","format":"uuid"}},{"name":"accountId","in":"path","required":true,"schema":{"type":"string","format":"uuid"}}],"responses":{"200":{"description":"Successful","content":{"application/json":{"schema":{"properties":{"statusCode":{"type":"integer","format":"int32"},"errorCode":{"type":"string"},"message":{"type":"string"},"data":{}}}}}},"400":{"description":"Please select a role to assign to the account","content":{"application/json":{"schema":{"properties":{"statusCode":{"type":"integer","format":"int32"},"errorCode":{"type":"string"},"message":{"type":"string"},"data":{"type":"object"}}},"example":"{\n  \"statusCode\": 400,\n  \"errorCode\": \"REQUIRED_FIELD_MISSING\",\n  \"message\": \"Please select a role to assign to the account\",\n  \"data\": null\n}\n"}}},"404":{"description":"Sorry, we couldn't find the role you are looking for","content":{"application/json":{"schema":{"properties":{"statusCode":{"type":"integer","format":"int32"},"errorCode":{"type":"string"},"message":{"type":"string"},"data":{"type":"object"}}},"example":"{\n  \"statusCode\": 404,\n  \"errorCode\": \"RESOURCE_NOT_FOUND\",\n  \"message\": \"Sorry, we couldn't find the role you are looking for\",\n  \"data\": null\n}\n"}}},"403":{"description":"You do not have sufficient permissions to revoke a role from the account.","content":{"application/json":{"schema":{"properties":{"statusCode":{"type":"integer","format":"int32"},"errorCode":{"type":"string"},"message":{"type":"string"},"data":{"type":"object"}}},"example":"{\n  \"statusCode\": 403,\n  \"errorCode\": \"FORBIDDEN\",\n  \"message\": \"You do not have sufficient permissions to revoke a role from the account.\",\n  \"data\": null\n}\n"}}},"409":{"description":"The role 'admin' was not found.","content":{"application/json":{"schema":{"properties":{"statusCode":{"type":"integer","format":"int32"},"errorCode":{"type":"string"},"message":{"type":"string"},"data":{"type":"object"}}},"example":"{\n  \"statusCode\": 409,\n  \"errorCode\": \"DUPLICATE_ENTRY\",\n  \"message\": \"The role 'admin' was not found.\",\n  \"data\": null\n}\n"}}}}}}},"components":{"schemas":{"PermissionResponse":{"properties":{"id":{"type":"string","format":"uuid"},"name":{"type":"string"},"key":{"type":"string"},"description":{"type":"string"}}},"GrantPermissionRequest":{"type":"object","properties":{"permissionKeys":{"type":"array","items":{"type":"string"},"uniqueItems":true}}},"AddRoleRequest":{"type":"object","properties":{"name":{"type":"string"},"key":{"type":"string"},"type":{"type":"string"},"description":{"type":"string"},"level":{"type":"integer","format":"int32"},"permissionKeys":{"type":"array","items":{"type":"string"},"uniqueItems":true}}},"RegisterBasicRequest":{"type":"object","properties":{"username":{"type":"string"},"password":{"type":"string"},"email":{"type":"string"},"phoneNumber":{"type":"string"},"provider":{"type":"string"}}}},"securitySchemes":{"bearerAuth":{"type":"http","scheme":"bearer","bearerFormat":"JWT"}}}}